alephonenull/__init__.py
alephonenull/core.py
alephonenull/providers.py
alephonenull/core/__init__.py
alephonenull/core/alephonenull_framework.py
alephonenull/core/detector.py
alephonenull/core/nullifier.py
alephonenull/core/patterns.py
alephonenull/inference/__init__.py
alephonenull/inference/protection.py
alephonenull/monitoring/__init__.py
alephonenull/monitoring/dashboard.py
alephonenull/monitoring/metrics.py
alephonenull/providers/__init__.py
alephonenull/providers/universal.py
alephonenull/utils/__init__.py
alephonenull_experimental-0.1.0a1.dist-info/licenses/LICENSE
alephonenull_experimental-0.1.0a1.dist-info/METADATA
alephonenull_experimental-0.1.0a1.dist-info/WHEEL
alephonenull_experimental-0.1.0a1.dist-info/entry_points.txt
alephonenull_experimental-0.1.0a1.dist-info/top_level.txt
alephonenull_experimental-0.1.0a1.dist-info/RECORD
