Metadata-Version: 2.4
Name: alephonenull-experimental
Version: 0.1.0a1
Summary: ⚠️ EXPERIMENTAL: Theoretical AI safety framework - research purposes only
Home-page: https://github.com/purposefulmaker/alephonenull
Author: AlephOneNull Research Team
Author-email: research@alephonenull.org
License: MIT
Project-URL: Bug Reports, https://github.com/purposefulmaker/alephonenull/issues
Project-URL: Source, https://github.com/purposefulmaker/alephonenull
Project-URL: Documentation, https://alephonenull.org/docs
Project-URL: Disclaimer, https://github.com/purposefulmaker/alephonenull/blob/main/DISCLAIMER.md
Classifier: Development Status :: 2 - Pre-Alpha
Classifier: Intended Audience :: Science/Research
Classifier: Topic :: Scientific/Engineering :: Artificial Intelligence
Classifier: Topic :: Scientific/Engineering :: Information Analysis
Classifier: License :: OSI Approved :: MIT License
Classifier: Programming Language :: Python :: 3
Classifier: Programming Language :: Python :: 3.8
Classifier: Programming Language :: Python :: 3.9
Classifier: Programming Language :: Python :: 3.10
Classifier: Programming Language :: Python :: 3.11
Classifier: Programming Language :: Python :: 3.12
Classifier: Environment :: No Input/Output (Daemon)
Classifier: Operating System :: OS Independent
Classifier: Natural Language :: English
Requires-Python: >=3.8
License-File: LICENSE
Requires-Dist: numpy>=1.21.0
Requires-Dist: sentence-transformers>=2.2.0
Requires-Dist: torch>=2.0.0
Requires-Dist: tiktoken>=0.3.0
Requires-Dist: prometheus-client>=0.16.0
Requires-Dist: fastapi>=0.95.0
Requires-Dist: uvicorn>=0.21.0
Provides-Extra: all-providers
Requires-Dist: openai>=1.0.0; extra == "all-providers"
Requires-Dist: anthropic>=0.3.0; extra == "all-providers"
Requires-Dist: google-generativeai>=0.3.0; extra == "all-providers"
Requires-Dist: transformers>=4.30.0; extra == "all-providers"
Requires-Dist: replicate>=0.15.0; extra == "all-providers"
Requires-Dist: cohere>=4.0.0; extra == "all-providers"
Requires-Dist: boto3>=1.26.0; extra == "all-providers"
Requires-Dist: azure-cognitiveservices-language-luis>=0.7.0; extra == "all-providers"
Provides-Extra: monitoring
Requires-Dist: grafana-api>=1.0.0; extra == "monitoring"
Requires-Dist: influxdb-client>=1.36.0; extra == "monitoring"
Requires-Dist: prometheus-client>=0.16.0; extra == "monitoring"
Requires-Dist: psutil>=5.9.0; extra == "monitoring"
Provides-Extra: dev
Requires-Dist: pytest>=7.0.0; extra == "dev"
Requires-Dist: pytest-asyncio>=0.21.0; extra == "dev"
Requires-Dist: black>=22.0.0; extra == "dev"
Requires-Dist: mypy>=1.0.0; extra == "dev"
Requires-Dist: coverage>=7.0.0; extra == "dev"
Requires-Dist: pre-commit>=3.0.0; extra == "dev"
Dynamic: author
Dynamic: author-email
Dynamic: classifier
Dynamic: description
Dynamic: description-content-type
Dynamic: home-page
Dynamic: license
Dynamic: license-file
Dynamic: project-url
Dynamic: provides-extra
Dynamic: requires-dist
Dynamic: requires-python
Dynamic: summary
